simpleprogress/__init__.py
simpleprogress-0.1.dist-info/DESCRIPTION.rst
simpleprogress-0.1.dist-info/METADATA
simpleprogress-0.1.dist-info/RECORD
simpleprogress-0.1.dist-info/WHEEL
simpleprogress-0.1.dist-info/metadata.json
simpleprogress-0.1.dist-info/top_level.txt
