Metadata-Version: 2.0
Name: simpleprogress
Version: 0.1
Summary: Simple progress indicator printing to stdout
Home-page: https://github.com/bmbove/simpleprogress
Author: Brian Bove
Author-email: brian@ufmsystems.com
License: MIT
Keywords: progress
Platform: UNKNOWN
Classifier: Programming Language :: Python :: 3
Classifier: License :: OSI Approved :: MIT License
Classifier: Operating System :: OS Independent
